[
  {
    "symbol": "VTL",
    "side": "long",
    "quantity": 80,
    "entryPrice": 658.7,
    "exitPrice": 634,
    "entryTime": "2026-06-19T07:04:50.001Z",
    "exitTime": "2026-07-09T04:13:00.000Z",
    "notes": "",
    "setup": {
      "watchedSince": "2026-07-13T06:25:47.134Z",
      "stopLoss": 610,
      "target": null,
      "stage": "stage-2",
      "base": "base-1",
      "rsi": 66,
      "fiftyDayMa": 600,
      "technicalChecklist": {
        "ma-uptrend": true,
        "ma-stacked": true,
        "ma200-duration": true
      },
      "week52Low": 390,
      "week52High": 666,
      "weeksInBase": 6,
      "vcpContractions": [
        {
          "high": 636,
          "low": 581
        },
        {
          "high": 619,
          "low": 576
        },
        {
          "high": 631,
          "low": 614
        },
        {
          "high": 637,
          "low": 626
        }
      ],
      "finalChecks": {
        "volume-price-quiet": true,
        "weak-holders-shaken-out": true,
        "volume-confirms-breakout": true,
        "minimal-overhead-resistance": true
      },
      "rating": {
        "ratio": 0.6,
        "rawRatio": 0.9166666666666666,
        "criteria": [
          {
            "id": "stop-placement",
            "weight": 1,
            "score": 1
          },
          {
            "id": "stage-quality",
            "weight": 2,
            "score": 1
          },
          {
            "id": "base-quality",
            "weight": 1,
            "score": 1
          },
          {
            "id": "ma-trend",
            "weight": 1,
            "score": 1
          },
          {
            "id": "relative-strength",
            "weight": 1,
            "score": 0
          },
          {
            "id": "week-range",
            "weight": 2,
            "score": 1
          },
          {
            "id": "vcp-structure",
            "weight": 3,
            "score": 1
          },
          {
            "id": "final-checks",
            "weight": 1,
            "score": 1
          }
        ],
        "gates": [
          {
            "id": "stage-2",
            "state": "pass",
            "cap": 0.4
          },
          {
            "id": "trend-template",
            "state": "pass",
            "cap": 0.6
          },
          {
            "id": "logical-stop",
            "state": "pass",
            "cap": 0.6
          },
          {
            "id": "real-base",
            "state": "pass",
            "cap": 0.6
          },
          {
            "id": "breakout-confirmation",
            "state": "fail",
            "cap": 0.6
          }
        ]
      }
    },
    "id": "l0yKsO-C7nk",
    "exitLearnings": [
      {
        "reason": "stopped-as-planned",
        "note": "It broke 20 MA & falling since last three days."
      },
      {
        "reason": "mistake-missed-signal",
        "note": "Yes, missed exit signal on July 06. Should I have existed on this day, it was clear sign with volume & shooting star candle. However, day before it was good progress & showing nice profits, so ignored the actual sign, in the hope 1st winner."
      }
    ]
  },
  {
    "symbol": "NHPC",
    "side": "long",
    "quantity": 400,
    "entryPrice": 87.09,
    "exitPrice": 85.8,
    "entryTime": "2025-10-06T03:45:15.000Z",
    "exitTime": "2025-10-10T04:45:00.000Z",
    "notes": "",
    "setup": {
      "watchedSince": "2025-09-01T09:46:54.830Z",
      "stopLoss": 86.34,
      "target": 91.03,
      "stage": "stage-1",
      "base": "base-4",
      "rsi": 59,
      "fiftyDayMa": 83,
      "technicalChecklist": {},
      "week52Low": 72,
      "week52High": 88,
      "weeksInBase": 2,
      "vcpContractions": [
        {
          "high": 88,
          "low": 83
        },
        {
          "high": 87,
          "low": 85
        }
      ],
      "finalChecks": {},
      "rating": {
        "ratio": 0.24285714285714288,
        "rawRatio": 0.24285714285714288,
        "criteria": [
          {
            "id": "risk-reward",
            "weight": 2,
            "score": 0
          },
          {
            "id": "stop-placement",
            "weight": 1,
            "score": 0
          },
          {
            "id": "stage-quality",
            "weight": 2,
            "score": 0
          },
          {
            "id": "base-quality",
            "weight": 1,
            "score": 0
          },
          {
            "id": "ma-trend",
            "weight": 1,
            "score": 0
          },
          {
            "id": "relative-strength",
            "weight": 1,
            "score": 0
          },
          {
            "id": "week-range",
            "weight": 2,
            "score": 0.5
          },
          {
            "id": "vcp-structure",
            "weight": 3,
            "score": 0.8
          },
          {
            "id": "final-checks",
            "weight": 1,
            "score": 0
          }
        ],
        "gates": [
          {
            "id": "stage-2",
            "state": "fail",
            "cap": 0.4
          },
          {
            "id": "trend-template",
            "state": "fail",
            "cap": 0.6
          },
          {
            "id": "logical-stop",
            "state": "fail",
            "cap": 0.6
          },
          {
            "id": "real-base",
            "state": "fail",
            "cap": 0.6
          },
          {
            "id": "breakout-confirmation",
            "state": "fail",
            "cap": 0.6
          }
        ]
      }
    },
    "id": "aARvVPxy8EY",
    "exitLearnings": [
      {
        "reason": "stopped-as-planned",
        "note": "Honored the ₹86.34 stop when the first hourly candle closed below it on Day 3 — no second-guessing, no waiting for a miracle."
      },
      {
        "reason": "mistake-emotional",
        "note": "15-second FOMO entry right at market open — excitement over strategy, no time to see if the breakout was real before jumping in."
      }
    ]
  },
  {
    "symbol": "BEL",
    "side": "long",
    "quantity": 80,
    "entryPrice": 413.6,
    "exitPrice": 408.65,
    "entryTime": "2025-10-06T08:31:28.000Z",
    "exitTime": "2025-10-08T04:45:47.000Z",
    "notes": "",
    "setup": {
      "watchedSince": "2025-09-25T10:03:11.156Z",
      "stopLoss": 409,
      "target": 432,
      "stage": "transition-1-2",
      "base": "base-1",
      "rsi": 60,
      "fiftyDayMa": 390,
      "technicalChecklist": {
        "ma-uptrend": true,
        "ma-stacked": true,
        "ma200-duration": true
      },
      "week52Low": 363,
      "week52High": 432,
      "weeksInBase": 3,
      "vcpContractions": [
        {
          "high": 417,
          "low": 393
        },
        {
          "high": 415,
          "low": 403
        }
      ],
      "finalChecks": {},
      "rating": {
        "ratio": 0.4,
        "rawRatio": 0.42857142857142855,
        "criteria": [
          {
            "id": "risk-reward",
            "weight": 2,
            "score": 0
          },
          {
            "id": "stop-placement",
            "weight": 1,
            "score": 0
          },
          {
            "id": "stage-quality",
            "weight": 2,
            "score": 0.3
          },
          {
            "id": "base-quality",
            "weight": 1,
            "score": 1
          },
          {
            "id": "ma-trend",
            "weight": 1,
            "score": 1
          },
          {
            "id": "relative-strength",
            "weight": 1,
            "score": 0
          },
          {
            "id": "week-range",
            "weight": 2,
            "score": 0.5
          },
          {
            "id": "vcp-structure",
            "weight": 3,
            "score": 0.8
          },
          {
            "id": "final-checks",
            "weight": 1,
            "score": 0
          }
        ],
        "gates": [
          {
            "id": "stage-2",
            "state": "fail",
            "cap": 0.4
          },
          {
            "id": "trend-template",
            "state": "fail",
            "cap": 0.6
          },
          {
            "id": "logical-stop",
            "state": "fail",
            "cap": 0.6
          },
          {
            "id": "real-base",
            "state": "fail",
            "cap": 0.6
          },
          {
            "id": "breakout-confirmation",
            "state": "fail",
            "cap": 0.6
          }
        ]
      }
    },
    "id": "yT8cmCmyv80",
    "exitLearnings": [
      {
        "reason": "stopped-as-planned",
        "note": "Honored the ₹409 stop the moment the hourly candle closed below it — no second-guessing, no waiting for a miracle."
      },
      {
        "reason": "mistake-emotional",
        "note": "Entry driven by emotion, not logic — was compensating for the losing NHPC trade that same morning and convinced myself a late-day entry meant patience when it was really FOMO."
      }
    ]
  },
  {
    "symbol": "TORNTPHARM",
    "side": "long",
    "quantity": 12,
    "entryPrice": 4687,
    "exitPrice": 4362.5,
    "entryTime": "2026-05-25T10:28:25.327Z",
    "exitTime": "2026-06-01T08:35:00.000Z",
    "notes": "",
    "setup": {
      "watchedSince": "2026-04-01T10:17:35.042Z",
      "stopLoss": 4200,
      "target": null,
      "stage": "transition-1-2",
      "base": "base-4",
      "rsi": 66,
      "fiftyDayMa": 4265,
      "technicalChecklist": {
        "ma-stacked": true,
        "ma-uptrend": true,
        "ma200-duration": true
      },
      "week52Low": 3404,
      "week52High": 4712,
      "weeksInBase": 2,
      "vcpContractions": [
        {
          "high": 4560,
          "low": 4262
        }
      ],
      "finalChecks": {
        "group-positive": true,
        "volume-confirms-breakout": true,
        "minimal-overhead-resistance": true
      },
      "rating": {
        "ratio": 0.4,
        "rawRatio": 0.4694444444444444,
        "criteria": [
          {
            "id": "stop-placement",
            "weight": 1,
            "score": 0.5
          },
          {
            "id": "stage-quality",
            "weight": 2,
            "score": 0.3
          },
          {
            "id": "base-quality",
            "weight": 1,
            "score": 0
          },
          {
            "id": "ma-trend",
            "weight": 1,
            "score": 1
          },
          {
            "id": "relative-strength",
            "weight": 1,
            "score": 0
          },
          {
            "id": "week-range",
            "weight": 2,
            "score": 1
          },
          {
            "id": "vcp-structure",
            "weight": 3,
            "score": 0.4
          },
          {
            "id": "final-checks",
            "weight": 1,
            "score": 0.3333333333333333
          }
        ],
        "gates": [
          {
            "id": "stage-2",
            "state": "fail",
            "cap": 0.4
          },
          {
            "id": "trend-template",
            "state": "pass",
            "cap": 0.6
          },
          {
            "id": "logical-stop",
            "state": "fail",
            "cap": 0.6
          },
          {
            "id": "real-base",
            "state": "fail",
            "cap": 0.6
          },
          {
            "id": "breakout-confirmation",
            "state": "fail",
            "cap": 0.6
          }
        ]
      }
    },
    "id": "DEl1oi8NQhE",
    "exitLearnings": [
      {
        "reason": "stopped-as-planned",
        "note": "Stop closed below 20 Day MA. With sharp decline in the price, since I bought. Huge red bar a day before with heavy volume"
      },
      {
        "reason": "mistake-early-entry",
        "note": "Jumped in before the base was actually ready. After getting stopped out, the stock stabilized, carved out a clean 3-T VCP, and gave a proper breakout signal on June 29 around ₹4,617. Price kept climbing from there — trading around ₹4,951 as of July 13, up ~7.2% from that signal. The real trade was the one I exited before it even started."
      }
    ]
  },
  {
    "symbol": "ONGC",
    "side": "long",
    "quantity": 200,
    "entryPrice": 297,
    "exitPrice": 283.25,
    "entryTime": "2026-04-28T03:04:55.215Z",
    "exitTime": "2026-05-06T08:26:00.000Z",
    "notes": "",
    "setup": {
      "watchedSince": "2026-04-01T02:58:21.419Z",
      "stopLoss": 280,
      "target": null,
      "stage": "transition-1-2",
      "base": "base-1",
      "rsi": 72,
      "fiftyDayMa": 277,
      "technicalChecklist": {
        "ma-uptrend": true,
        "ma-stacked": true,
        "ma200-duration": true
      },
      "week52Low": 220,
      "week52High": 300,
      "weeksInBase": 8,
      "vcpContractions": [
        {
          "high": 292,
          "low": 257
        },
        {
          "high": 292,
          "low": 274
        }
      ],
      "finalChecks": {
        "volume-price-quiet": false,
        "weak-holders-shaken-out": false,
        "volume-confirms-breakout": true,
        "minimal-overhead-resistance": true
      },
      "rating": {
        "ratio": 0.4,
        "rawRatio": 0.7277777777777779,
        "criteria": [
          {
            "id": "stop-placement",
            "weight": 1,
            "score": 0.5
          },
          {
            "id": "stage-quality",
            "weight": 2,
            "score": 0.3
          },
          {
            "id": "base-quality",
            "weight": 1,
            "score": 1
          },
          {
            "id": "ma-trend",
            "weight": 1,
            "score": 1
          },
          {
            "id": "relative-strength",
            "weight": 1,
            "score": 0.3
          },
          {
            "id": "week-range",
            "weight": 2,
            "score": 1
          },
          {
            "id": "vcp-structure",
            "weight": 3,
            "score": 1
          },
          {
            "id": "final-checks",
            "weight": 1,
            "score": 0.3333333333333333
          }
        ],
        "gates": [
          {
            "id": "stage-2",
            "state": "fail",
            "cap": 0.4
          },
          {
            "id": "trend-template",
            "state": "pass",
            "cap": 0.6
          },
          {
            "id": "logical-stop",
            "state": "fail",
            "cap": 0.6
          },
          {
            "id": "real-base",
            "state": "pass",
            "cap": 0.6
          },
          {
            "id": "breakout-confirmation",
            "state": "fail",
            "cap": 0.6
          }
        ]
      }
    },
    "id": "b-8RmSVTZcA",
    "exitLearnings": [
      {
        "reason": "stopped-as-planned",
        "note": "stock went up & crashed below 20 DAY MA. closed the stock as planned."
      },
      {
        "reason": "mistake-broke-rule",
        "note": "need to understand more on the good setups, it seems it was good, but when i looked overall after a trade. it seems i missed few pointer, need to very careful with making good selection"
      }
    ]
  }
]
